sbrowser/__init__.py
sbrowser/adjust_mimes.py
sbrowser/betbrowser.py
sbrowser/browser.py
sbrowser/fullscreen.py
sbrowser/tool.py
sbrowser/utils.py
sbrowser-0.0.23.data/scripts/fullscreenshot
sbrowser-0.0.23.data/scripts/fullscreenshot.cmd
sbrowser-0.0.23.data/scripts/sbrowser
sbrowser-0.0.23.data/scripts/sbrowser.cmd
sbrowser-0.0.23.data/scripts/screenshot
sbrowser-0.0.23.data/scripts/screenshot.cmd
sbrowser-0.0.23.data/scripts/webbrowser
sbrowser-0.0.23.data/scripts/webbrowser.cmd
sbrowser-0.0.23.dist-info/DESCRIPTION.rst
sbrowser-0.0.23.dist-info/METADATA
sbrowser-0.0.23.dist-info/RECORD
sbrowser-0.0.23.dist-info/WHEEL
sbrowser-0.0.23.dist-info/metadata.json
sbrowser-0.0.23.dist-info/top_level.txt
webbrowser/__init__.py
webbrowser/betbrowser.py
webbrowser/browser.py
webbrowser/fullscreen.py
webbrowser/tool.py
