Metadata-Version: 2.0
Name: sbrowser
Version: 0.0.23
Summary: Python library for automate web browser.
Home-page: https://github.com/tuaplicacionpropia/webbrowser
Author: tuaplicacionpropia.com
Author-email: tuaplicacionpropia@gmail.com
License: MIT
Download-URL: https://github.com/tuaplicacionpropia/webbrowser/archive/master.zip
Keywords: web,browser,selenium
Platform: any
Classifier: Development Status :: 4 - Beta
Classifier: License :: OSI Approved :: MIT License
Classifier: Programming Language :: Python
Classifier: Programming Language :: Python :: 2.7
Classifier: Intended Audience :: Developers
Classifier: Topic :: Multimedia :: Graphics
Requires-Dist: Pillow (>=3.4.2)
Requires-Dist: autopy (>=1.1.1)
Requires-Dist: clipboard (>=0.0.4)
Requires-Dist: hjson (>=2.0.2)
Requires-Dist: numpy (>=1.12.0b1)
Requires-Dist: pyscreenshot (>=0.4.2)
Requires-Dist: rarfile (>=3.0)
Requires-Dist: requests (>=2.21.0)
Requires-Dist: selenium (>=3.11.0)
